gsmodutils/__init__.py
gsmodutils/cli.py
gsmodutils/cliutils.py
gsmodutils/design.py
gsmodutils/exceptions.py
gsmodutils/metacyc.py
gsmodutils/model_diff.py
gsmodutils/project.py
gsmodutils/project_config.py
gsmodutils/scrumpy.py
gsmodutils/tester.py
gsmodutils/testutils.py
gsmodutils/utils.py
gsmodutils/validator.py
gsmodutils/project/__init__.py
gsmodutils/project/design.py
gsmodutils/project/interface.py
gsmodutils/project/model.py
gsmodutils/project/project_config.py
gsmodutils/templates/Dockerfile
gsmodutils/templates/requirements.txt
gsmodutils/test/__init__.py
gsmodutils/test/instances.py
gsmodutils/test/tester.py
gsmodutils/test/utils.py
gsmodutils/utils/__init__.py
gsmodutils/utils/io.py
gsmodutils/utils/metacyc.py
gsmodutils/utils/scrumpy.py
gsmodutils/utils/validator.py
tests/.coverage
tests/.coveragerc
tests/__init__.py
tests/__init__.pyc
tests/conftest.py
tests/fake_test_env.py
tests/test_cli.py
tests/test_designs.py
tests/test_diff.py
tests/test_diff.pyc
tests/test_metacyc.py
tests/test_model.py
tests/test_project.py
tests/test_project_config.py
tests/test_scrumpy.py
tests/test_tests.py
tests/test_utils.py
gsmodutils-0.0.4.dist-info/LICENSE
gsmodutils-0.0.4.dist-info/METADATA
gsmodutils-0.0.4.dist-info/WHEEL
gsmodutils-0.0.4.dist-info/entry_points.txt
gsmodutils-0.0.4.dist-info/top_level.txt
gsmodutils-0.0.4.dist-info/RECORD
