Metadata-Version: 2.1
Name: gsmodutils
Version: 0.0.4
Summary: Utilities for the management and testing of genome scale models in  a cross platform, open manner.
Home-page: UNKNOWN
Author: James Gilbert
Author-email: james.gilbert@nottingham.ac.uk
License: Apache
Platform: GNU/Linux
Platform: Mac OS X >= 10.7
Platform: Microsoft Windows >= 7
Classifier: Environment :: Console
Classifier: Intended Audience :: Science/Research
Classifier: License :: OSI Approved :: Apache Software License
Classifier: Operating System :: OS Independent
Classifier: Programming Language :: Python :: 2.7
Classifier: Programming Language :: Python :: 3.4
Classifier: Programming Language :: Python :: 3.5
Classifier: Programming Language :: Python :: 3.6
Classifier: Programming Language :: Python :: 3.7
Classifier: Programming Language :: Python :: Implementation :: CPython
Classifier: Topic :: Scientific/Engineering
Classifier: Topic :: Scientific/Engineering :: Bio-Informatics
Requires-Dist: cobra (>=0.13.4)
Requires-Dist: pytest (>=3.6.0)
Requires-Dist: click (>=6.7)
Requires-Dist: lockfile (>=0.12.2)
Requires-Dist: pytest-cov (>=2.5.1)
Requires-Dist: pytest-xdist (>=1.18.1)
Requires-Dist: python-libsbml (>=5.15.0)
Requires-Dist: pandas (>=0.20.3)
Requires-Dist: six (>=1.10.0)
Requires-Dist: plotly (>=2.0.14)
Requires-Dist: sphinx-click (>=1.0.3)
Requires-Dist: docker (>=2.6.1)
Requires-Dist: lxml (>=4.1.1)
Requires-Dist: fasteners (>=0.14.1)
Requires-Dist: tqdm (>=4.23.3)
Requires-Dist: jsonschema (>=2.6.0)
